aixhello/__init__.py
aixhello/xyello.cp312-win_amd64.pyd
aixhello-5.16.dist-info/LICENSE
aixhello-5.16.dist-info/METADATA
aixhello-5.16.dist-info/WHEEL
aixhello-5.16.dist-info/top_level.txt
aixhello-5.16.dist-info/RECORD
