Metadata-Version: 2.1
Name: aixhello
Version: 5.16
Summary: AI HRM Package
Author: SecureAI
Author-email: package@xerocai.com
Classifier: Programming Language :: Python :: 3
Classifier: License :: OSI Approved :: MIT License
Classifier: Operating System :: OS Independent
Requires-Python: >=3.6
License-File: LICENSE
Requires-Dist: requests
Requires-Dist: cryptography
Requires-Dist: openai
